{"iterations": 0, "train_loss": 2.5587730633402335, "test_loss": 2.03127884163576, "Accuracy": 0.30330882352941174, "time_this_iter_s": 24.569204807281494, "done": false, "training_iteration": 1, "trial_id": "d1db5e8d", "date": "2023-06-06_11-17-35", "timestamp": 1686050255, "time_total_s": 24.569204807281494, "pid": 5558, "hostname": "8fa062c8815e", "node_ip": "172.17.0.3", "config": {"input_size": 13, "output_size": 20, "tune_dir": "/workspaces/MLopdracht/models/ray", "data_dir": "/workspaces/MLopdracht/data/raw", "hidden_size": 64, "dropout": 0.20002091911275133, "num_layers": 3}, "time_since_restore": 24.569204807281494, "iterations_since_restore": 1}
