{"iterations": 0, "train_loss": 2.3752663257052595, "test_loss": 1.5970627981073715, "Accuracy": 0.5119485294117647, "time_this_iter_s": 40.3163046836853, "done": false, "training_iteration": 1, "trial_id": "1181021a", "date": "2023-06-06_15-12-07", "timestamp": 1686064327, "time_total_s": 40.3163046836853, "pid": 30788, "hostname": "8fa062c8815e", "node_ip": "172.17.0.3", "config": {"input_size": 13, "output_size": 20, "tune_dir": "/workspaces/MLopdracht/models/ray", "data_dir": "/workspaces/MLopdracht/data/raw", "hidden_size": 88, "dropout": 0.1672842572787482, "num_layers": 3}, "time_since_restore": 40.3163046836853, "iterations_since_restore": 1}
{"iterations": 0, "train_loss": 2.4550347241383155, "test_loss": 1.826618815169615, "Accuracy": 0.4117647058823529, "time_this_iter_s": 35.86965227127075, "done": false, "timesteps_total": 0, "episodes_total": 0, "training_iteration": 1, "trial_id": "1181021a", "date": "2023-06-06_15-16-29", "timestamp": 1686064589, "time_total_s": 76.18595695495605, "pid": 30773, "hostname": "8fa062c8815e", "node_ip": "172.17.0.3", "config": {"input_size": 13, "output_size": 20, "tune_dir": "/workspaces/MLopdracht/models/ray", "data_dir": "/workspaces/MLopdracht/data/raw", "hidden_size": 88, "dropout": 0.1672842572787482, "num_layers": 3}, "time_since_restore": 35.86965227127075, "iterations_since_restore": 1}
{"iterations": 1, "train_loss": 1.0986738413282968, "test_loss": 0.8670975491404533, "Accuracy": 0.7394301470588235, "time_this_iter_s": 33.99541735649109, "done": false, "timesteps_total": 0, "episodes_total": 0, "training_iteration": 2, "trial_id": "1181021a", "date": "2023-06-06_15-17-03", "timestamp": 1686064623, "time_total_s": 110.18137431144714, "pid": 30773, "hostname": "8fa062c8815e", "node_ip": "172.17.0.3", "config": {"input_size": 13, "output_size": 20, "tune_dir": "/workspaces/MLopdracht/models/ray", "data_dir": "/workspaces/MLopdracht/data/raw", "hidden_size": 88, "dropout": 0.1672842572787482, "num_layers": 3}, "time_since_restore": 69.86506962776184, "iterations_since_restore": 2}
{"iterations": 2, "train_loss": 0.4408910751198102, "test_loss": 0.9426129881073447, "Accuracy": 0.796875, "time_this_iter_s": 35.22305750846863, "done": false, "timesteps_total": 0, "episodes_total": 0, "training_iteration": 3, "trial_id": "1181021a", "date": "2023-06-06_15-17-38", "timestamp": 1686064658, "time_total_s": 145.40443181991577, "pid": 30773, "hostname": "8fa062c8815e", "node_ip": "172.17.0.3", "config": {"input_size": 13, "output_size": 20, "tune_dir": "/workspaces/MLopdracht/models/ray", "data_dir": "/workspaces/MLopdracht/data/raw", "hidden_size": 88, "dropout": 0.1672842572787482, "num_layers": 3}, "time_since_restore": 105.08812713623047, "iterations_since_restore": 3}
