{"iterations": 0, "train_loss": 2.3309063593160757, "test_loss": 1.5542064098750843, "Accuracy": 0.5009191176470589, "time_this_iter_s": 51.98946738243103, "done": false, "training_iteration": 1, "trial_id": "6abc626f", "date": "2023-06-06_11-23-07", "timestamp": 1686050587, "time_total_s": 51.98946738243103, "pid": 14261, "hostname": "8fa062c8815e", "node_ip": "172.17.0.3", "config": {"input_size": 13, "output_size": 20, "tune_dir": "/workspaces/MLopdracht/models/ray", "data_dir": "/workspaces/MLopdracht/data/raw", "hidden_size": 104, "dropout": 0.2660308010009219, "num_layers": 4}, "time_since_restore": 51.98946738243103, "iterations_since_restore": 1}
{"iterations": 0, "train_loss": 2.4109782929559356, "test_loss": 1.9224906581289627, "Accuracy": 0.36672794117647056, "time_this_iter_s": 53.61463522911072, "done": false, "timesteps_total": 0, "episodes_total": 0, "training_iteration": 1, "trial_id": "6abc626f", "date": "2023-06-06_11-26-23", "timestamp": 1686050783, "time_total_s": 105.60410261154175, "pid": 14381, "hostname": "8fa062c8815e", "node_ip": "172.17.0.3", "config": {"input_size": 13, "output_size": 20, "tune_dir": "/workspaces/MLopdracht/models/ray", "data_dir": "/workspaces/MLopdracht/data/raw", "hidden_size": 104, "dropout": 0.2660308010009219, "num_layers": 4}, "time_since_restore": 53.61463522911072, "iterations_since_restore": 1}
{"iterations": 1, "train_loss": 1.063175959060493, "test_loss": 0.7656924150445882, "Accuracy": 0.7679227941176471, "time_this_iter_s": 38.33082437515259, "done": false, "timesteps_total": 0, "episodes_total": 0, "training_iteration": 2, "trial_id": "6abc626f", "date": "2023-06-06_11-27-01", "timestamp": 1686050821, "time_total_s": 143.93492698669434, "pid": 14381, "hostname": "8fa062c8815e", "node_ip": "172.17.0.3", "config": {"input_size": 13, "output_size": 20, "tune_dir": "/workspaces/MLopdracht/models/ray", "data_dir": "/workspaces/MLopdracht/data/raw", "hidden_size": 104, "dropout": 0.2660308010009219, "num_layers": 4}, "time_since_restore": 91.9454596042633, "iterations_since_restore": 2}
{"iterations": 2, "train_loss": 0.3562631173402939, "test_loss": 0.40274659785277706, "Accuracy": 0.8924632352941176, "time_this_iter_s": 30.47522521018982, "done": false, "timesteps_total": 0, "episodes_total": 0, "training_iteration": 3, "trial_id": "6abc626f", "date": "2023-06-06_11-27-31", "timestamp": 1686050851, "time_total_s": 174.41015219688416, "pid": 14381, "hostname": "8fa062c8815e", "node_ip": "172.17.0.3", "config": {"input_size": 13, "output_size": 20, "tune_dir": "/workspaces/MLopdracht/models/ray", "data_dir": "/workspaces/MLopdracht/data/raw", "hidden_size": 104, "dropout": 0.2660308010009219, "num_layers": 4}, "time_since_restore": 122.42068481445312, "iterations_since_restore": 3}
{"iterations": 0, "train_loss": 2.403963592445966, "test_loss": 1.6300297361962937, "Accuracy": 0.47058823529411764, "time_this_iter_s": 25.30453085899353, "done": false, "timesteps_total": 0, "episodes_total": 0, "training_iteration": 1, "trial_id": "6abc626f", "date": "2023-06-06_11-28-20", "timestamp": 1686050900, "time_total_s": 199.71468305587769, "pid": 3588, "hostname": "8fa062c8815e", "node_ip": "172.17.0.3", "config": {"input_size": 13, "output_size": 20, "tune_dir": "/workspaces/MLopdracht/models/ray", "data_dir": "/workspaces/MLopdracht/data/raw", "hidden_size": 104, "dropout": 0.2660308010009219, "num_layers": 4}, "time_since_restore": 25.30453085899353, "iterations_since_restore": 1}
{"iterations": 1, "train_loss": 0.9982207203374326, "test_loss": 0.7787361631498617, "Accuracy": 0.7752757352941176, "time_this_iter_s": 24.911410093307495, "done": false, "timesteps_total": 0, "episodes_total": 0, "training_iteration": 2, "trial_id": "6abc626f", "date": "2023-06-06_11-28-45", "timestamp": 1686050925, "time_total_s": 224.62609314918518, "pid": 3588, "hostname": "8fa062c8815e", "node_ip": "172.17.0.3", "config": {"input_size": 13, "output_size": 20, "tune_dir": "/workspaces/MLopdracht/models/ray", "data_dir": "/workspaces/MLopdracht/data/raw", "hidden_size": 104, "dropout": 0.2660308010009219, "num_layers": 4}, "time_since_restore": 50.215940952301025, "iterations_since_restore": 2}
{"iterations": 2, "train_loss": 0.33503156480858626, "test_loss": 0.33904687074177403, "Accuracy": 0.9260110294117647, "time_this_iter_s": 27.169231414794922, "done": false, "timesteps_total": 0, "episodes_total": 0, "training_iteration": 3, "trial_id": "6abc626f", "date": "2023-06-06_11-29-12", "timestamp": 1686050952, "time_total_s": 251.7953245639801, "pid": 3588, "hostname": "8fa062c8815e", "node_ip": "172.17.0.3", "config": {"input_size": 13, "output_size": 20, "tune_dir": "/workspaces/MLopdracht/models/ray", "data_dir": "/workspaces/MLopdracht/data/raw", "hidden_size": 104, "dropout": 0.2660308010009219, "num_layers": 4}, "time_since_restore": 77.38517236709595, "iterations_since_restore": 3}
{"iterations": 3, "train_loss": 0.18039896187273044, "test_loss": 0.296505810583339, "Accuracy": 0.9214154411764706, "time_this_iter_s": 25.414770364761353, "done": false, "timesteps_total": 0, "episodes_total": 0, "training_iteration": 4, "trial_id": "6abc626f", "date": "2023-06-06_11-29-37", "timestamp": 1686050977, "time_total_s": 277.21009492874146, "pid": 3588, "hostname": "8fa062c8815e", "node_ip": "172.17.0.3", "config": {"input_size": 13, "output_size": 20, "tune_dir": "/workspaces/MLopdracht/models/ray", "data_dir": "/workspaces/MLopdracht/data/raw", "hidden_size": 104, "dropout": 0.2660308010009219, "num_layers": 4}, "time_since_restore": 102.7999427318573, "iterations_since_restore": 4}
{"iterations": 4, "train_loss": 0.11488555186401003, "test_loss": 0.22349757879205487, "Accuracy": 0.9453125, "time_this_iter_s": 24.865644216537476, "done": false, "timesteps_total": 0, "episodes_total": 0, "training_iteration": 5, "trial_id": "6abc626f", "date": "2023-06-06_11-30-02", "timestamp": 1686051002, "time_total_s": 302.07573914527893, "pid": 3588, "hostname": "8fa062c8815e", "node_ip": "172.17.0.3", "config": {"input_size": 13, "output_size": 20, "tune_dir": "/workspaces/MLopdracht/models/ray", "data_dir": "/workspaces/MLopdracht/data/raw", "hidden_size": 104, "dropout": 0.2660308010009219, "num_layers": 4}, "time_since_restore": 127.66558694839478, "iterations_since_restore": 5}
{"iterations": 5, "train_loss": 0.07249587113761062, "test_loss": 0.27572344587294056, "Accuracy": 0.9379595588235294, "time_this_iter_s": 23.6386775970459, "done": false, "timesteps_total": 0, "episodes_total": 0, "training_iteration": 6, "trial_id": "6abc626f", "date": "2023-06-06_11-30-26", "timestamp": 1686051026, "time_total_s": 325.71441674232483, "pid": 3588, "hostname": "8fa062c8815e", "node_ip": "172.17.0.3", "config": {"input_size": 13, "output_size": 20, "tune_dir": "/workspaces/MLopdracht/models/ray", "data_dir": "/workspaces/MLopdracht/data/raw", "hidden_size": 104, "dropout": 0.2660308010009219, "num_layers": 4}, "time_since_restore": 151.30426454544067, "iterations_since_restore": 6}
{"iterations": 6, "train_loss": 0.06993394898865553, "test_loss": 0.19502520611893168, "Accuracy": 0.9554227941176471, "time_this_iter_s": 20.58274793624878, "done": false, "timesteps_total": 0, "episodes_total": 0, "training_iteration": 7, "trial_id": "6abc626f", "date": "2023-06-06_11-30-46", "timestamp": 1686051046, "time_total_s": 346.2971646785736, "pid": 3588, "hostname": "8fa062c8815e", "node_ip": "172.17.0.3", "config": {"input_size": 13, "output_size": 20, "tune_dir": "/workspaces/MLopdracht/models/ray", "data_dir": "/workspaces/MLopdracht/data/raw", "hidden_size": 104, "dropout": 0.2660308010009219, "num_layers": 4}, "time_since_restore": 171.88701248168945, "iterations_since_restore": 7}
{"iterations": 7, "train_loss": 0.06588411849733551, "test_loss": 0.15002686841933824, "Accuracy": 0.9618566176470589, "time_this_iter_s": 21.76248025894165, "done": false, "timesteps_total": 0, "episodes_total": 0, "training_iteration": 8, "trial_id": "6abc626f", "date": "2023-06-06_11-31-08", "timestamp": 1686051068, "time_total_s": 368.05964493751526, "pid": 3588, "hostname": "8fa062c8815e", "node_ip": "172.17.0.3", "config": {"input_size": 13, "output_size": 20, "tune_dir": "/workspaces/MLopdracht/models/ray", "data_dir": "/workspaces/MLopdracht/data/raw", "hidden_size": 104, "dropout": 0.2660308010009219, "num_layers": 4}, "time_since_restore": 193.6494927406311, "iterations_since_restore": 8}
{"iterations": 8, "train_loss": 0.03302501885387685, "test_loss": 0.20873328561291976, "Accuracy": 0.9508272058823529, "time_this_iter_s": 20.162153244018555, "done": false, "timesteps_total": 0, "episodes_total": 0, "training_iteration": 9, "trial_id": "6abc626f", "date": "2023-06-06_11-31-28", "timestamp": 1686051088, "time_total_s": 388.2217981815338, "pid": 3588, "hostname": "8fa062c8815e", "node_ip": "172.17.0.3", "config": {"input_size": 13, "output_size": 20, "tune_dir": "/workspaces/MLopdracht/models/ray", "data_dir": "/workspaces/MLopdracht/data/raw", "hidden_size": 104, "dropout": 0.2660308010009219, "num_layers": 4}, "time_since_restore": 213.81164598464966, "iterations_since_restore": 9}
{"iterations": 9, "train_loss": 0.03549967762941802, "test_loss": 0.15495473214575803, "Accuracy": 0.9595588235294118, "time_this_iter_s": 20.93826413154602, "done": false, "timesteps_total": 0, "episodes_total": 0, "training_iteration": 10, "trial_id": "6abc626f", "date": "2023-06-06_11-31-49", "timestamp": 1686051109, "time_total_s": 409.16006231307983, "pid": 3588, "hostname": "8fa062c8815e", "node_ip": "172.17.0.3", "config": {"input_size": 13, "output_size": 20, "tune_dir": "/workspaces/MLopdracht/models/ray", "data_dir": "/workspaces/MLopdracht/data/raw", "hidden_size": 104, "dropout": 0.2660308010009219, "num_layers": 4}, "time_since_restore": 234.74991011619568, "iterations_since_restore": 10}
{"iterations": 10, "train_loss": 0.027768134452556305, "test_loss": 0.14963869556702455, "Accuracy": 0.9650735294117647, "time_this_iter_s": 20.589313983917236, "done": false, "timesteps_total": 0, "episodes_total": 0, "training_iteration": 11, "trial_id": "6abc626f", "date": "2023-06-06_11-32-10", "timestamp": 1686051130, "time_total_s": 429.74937629699707, "pid": 3588, "hostname": "8fa062c8815e", "node_ip": "172.17.0.3", "config": {"input_size": 13, "output_size": 20, "tune_dir": "/workspaces/MLopdracht/models/ray", "data_dir": "/workspaces/MLopdracht/data/raw", "hidden_size": 104, "dropout": 0.2660308010009219, "num_layers": 4}, "time_since_restore": 255.33922410011292, "iterations_since_restore": 11}
{"iterations": 11, "train_loss": 0.02000093565365408, "test_loss": 0.12533784408622203, "Accuracy": 0.9710477941176471, "time_this_iter_s": 20.371044158935547, "done": false, "timesteps_total": 0, "episodes_total": 0, "training_iteration": 12, "trial_id": "6abc626f", "date": "2023-06-06_11-32-30", "timestamp": 1686051150, "time_total_s": 450.1204204559326, "pid": 3588, "hostname": "8fa062c8815e", "node_ip": "172.17.0.3", "config": {"input_size": 13, "output_size": 20, "tune_dir": "/workspaces/MLopdracht/models/ray", "data_dir": "/workspaces/MLopdracht/data/raw", "hidden_size": 104, "dropout": 0.2660308010009219, "num_layers": 4}, "time_since_restore": 275.71026825904846, "iterations_since_restore": 12}
{"iterations": 12, "train_loss": 0.028922911839066888, "test_loss": 0.2245334090651287, "Accuracy": 0.9503676470588235, "time_this_iter_s": 20.710548162460327, "done": false, "timesteps_total": 0, "episodes_total": 0, "training_iteration": 13, "trial_id": "6abc626f", "date": "2023-06-06_11-32-51", "timestamp": 1686051171, "time_total_s": 470.83096861839294, "pid": 3588, "hostname": "8fa062c8815e", "node_ip": "172.17.0.3", "config": {"input_size": 13, "output_size": 20, "tune_dir": "/workspaces/MLopdracht/models/ray", "data_dir": "/workspaces/MLopdracht/data/raw", "hidden_size": 104, "dropout": 0.2660308010009219, "num_layers": 4}, "time_since_restore": 296.4208164215088, "iterations_since_restore": 13}
{"iterations": 13, "train_loss": 0.02869058206668395, "test_loss": 0.1663509819225189, "Accuracy": 0.9604779411764706, "time_this_iter_s": 21.16987681388855, "done": false, "timesteps_total": 0, "episodes_total": 0, "training_iteration": 14, "trial_id": "6abc626f", "date": "2023-06-06_11-33-12", "timestamp": 1686051192, "time_total_s": 492.0008454322815, "pid": 3588, "hostname": "8fa062c8815e", "node_ip": "172.17.0.3", "config": {"input_size": 13, "output_size": 20, "tune_dir": "/workspaces/MLopdracht/models/ray", "data_dir": "/workspaces/MLopdracht/data/raw", "hidden_size": 104, "dropout": 0.2660308010009219, "num_layers": 4}, "time_since_restore": 317.59069323539734, "iterations_since_restore": 14}
{"iterations": 14, "train_loss": 0.03249284300277263, "test_loss": 0.16776853444068418, "Accuracy": 0.9572610294117647, "time_this_iter_s": 21.021909713745117, "done": false, "timesteps_total": 0, "episodes_total": 0, "training_iteration": 15, "trial_id": "6abc626f", "date": "2023-06-06_11-33-33", "timestamp": 1686051213, "time_total_s": 513.0227551460266, "pid": 3588, "hostname": "8fa062c8815e", "node_ip": "172.17.0.3", "config": {"input_size": 13, "output_size": 20, "tune_dir": "/workspaces/MLopdracht/models/ray", "data_dir": "/workspaces/MLopdracht/data/raw", "hidden_size": 104, "dropout": 0.2660308010009219, "num_layers": 4}, "time_since_restore": 338.61260294914246, "iterations_since_restore": 15}
{"iterations": 15, "train_loss": 0.018709226847101836, "test_loss": 0.5361055322470801, "Accuracy": 0.9172794117647058, "time_this_iter_s": 21.019695520401, "done": false, "timesteps_total": 0, "episodes_total": 0, "training_iteration": 16, "trial_id": "6abc626f", "date": "2023-06-06_11-33-54", "timestamp": 1686051234, "time_total_s": 534.0424506664276, "pid": 3588, "hostname": "8fa062c8815e", "node_ip": "172.17.0.3", "config": {"input_size": 13, "output_size": 20, "tune_dir": "/workspaces/MLopdracht/models/ray", "data_dir": "/workspaces/MLopdracht/data/raw", "hidden_size": 104, "dropout": 0.2660308010009219, "num_layers": 4}, "time_since_restore": 359.63229846954346, "iterations_since_restore": 16}
{"iterations": 16, "train_loss": 0.01916969972815211, "test_loss": 0.14792186661404283, "Accuracy": 0.9696691176470589, "time_this_iter_s": 20.79075026512146, "done": false, "timesteps_total": 0, "episodes_total": 0, "training_iteration": 17, "trial_id": "6abc626f", "date": "2023-06-06_11-34-15", "timestamp": 1686051255, "time_total_s": 554.8332009315491, "pid": 3588, "hostname": "8fa062c8815e", "node_ip": "172.17.0.3", "config": {"input_size": 13, "output_size": 20, "tune_dir": "/workspaces/MLopdracht/models/ray", "data_dir": "/workspaces/MLopdracht/data/raw", "hidden_size": 104, "dropout": 0.2660308010009219, "num_layers": 4}, "time_since_restore": 380.4230487346649, "iterations_since_restore": 17}
{"iterations": 17, "train_loss": 0.003722378993135633, "test_loss": 0.20316368461970022, "Accuracy": 0.9590992647058824, "time_this_iter_s": 20.567497491836548, "done": false, "timesteps_total": 0, "episodes_total": 0, "training_iteration": 18, "trial_id": "6abc626f", "date": "2023-06-06_11-34-35", "timestamp": 1686051275, "time_total_s": 575.4006984233856, "pid": 3588, "hostname": "8fa062c8815e", "node_ip": "172.17.0.3", "config": {"input_size": 13, "output_size": 20, "tune_dir": "/workspaces/MLopdracht/models/ray", "data_dir": "/workspaces/MLopdracht/data/raw", "hidden_size": 104, "dropout": 0.2660308010009219, "num_layers": 4}, "time_since_restore": 400.99054622650146, "iterations_since_restore": 18}
{"iterations": 18, "train_loss": 0.02479159538871473, "test_loss": 0.13823880807339103, "Accuracy": 0.9682904411764706, "time_this_iter_s": 20.49284267425537, "done": false, "timesteps_total": 0, "episodes_total": 0, "training_iteration": 19, "trial_id": "6abc626f", "date": "2023-06-06_11-34-56", "timestamp": 1686051296, "time_total_s": 595.893541097641, "pid": 3588, "hostname": "8fa062c8815e", "node_ip": "172.17.0.3", "config": {"input_size": 13, "output_size": 20, "tune_dir": "/workspaces/MLopdracht/models/ray", "data_dir": "/workspaces/MLopdracht/data/raw", "hidden_size": 104, "dropout": 0.2660308010009219, "num_layers": 4}, "time_since_restore": 421.48338890075684, "iterations_since_restore": 19}
{"iterations": 19, "train_loss": 0.018152164818337008, "test_loss": 0.27256715434658174, "Accuracy": 0.9315257352941176, "time_this_iter_s": 21.686675310134888, "done": false, "timesteps_total": 0, "episodes_total": 0, "training_iteration": 20, "trial_id": "6abc626f", "date": "2023-06-06_11-35-18", "timestamp": 1686051318, "time_total_s": 617.5802164077759, "pid": 3588, "hostname": "8fa062c8815e", "node_ip": "172.17.0.3", "config": {"input_size": 13, "output_size": 20, "tune_dir": "/workspaces/MLopdracht/models/ray", "data_dir": "/workspaces/MLopdracht/data/raw", "hidden_size": 104, "dropout": 0.2660308010009219, "num_layers": 4}, "time_since_restore": 443.1700642108917, "iterations_since_restore": 20}
{"iterations": 20, "train_loss": 0.03497002182078539, "test_loss": 0.32959567073061513, "Accuracy": 0.9407169117647058, "time_this_iter_s": 20.495200872421265, "done": false, "timesteps_total": 0, "episodes_total": 0, "training_iteration": 21, "trial_id": "6abc626f", "date": "2023-06-06_11-35-38", "timestamp": 1686051338, "time_total_s": 638.0754172801971, "pid": 3588, "hostname": "8fa062c8815e", "node_ip": "172.17.0.3", "config": {"input_size": 13, "output_size": 20, "tune_dir": "/workspaces/MLopdracht/models/ray", "data_dir": "/workspaces/MLopdracht/data/raw", "hidden_size": 104, "dropout": 0.2660308010009219, "num_layers": 4}, "time_since_restore": 463.665265083313, "iterations_since_restore": 21}
{"iterations": 21, "train_loss": 0.017523883099642864, "test_loss": 0.142540751826292, "Accuracy": 0.9696691176470589, "time_this_iter_s": 21.120354175567627, "done": false, "timesteps_total": 0, "episodes_total": 0, "training_iteration": 22, "trial_id": "6abc626f", "date": "2023-06-06_11-35-59", "timestamp": 1686051359, "time_total_s": 659.1957714557648, "pid": 3588, "hostname": "8fa062c8815e", "node_ip": "172.17.0.3", "config": {"input_size": 13, "output_size": 20, "tune_dir": "/workspaces/MLopdracht/models/ray", "data_dir": "/workspaces/MLopdracht/data/raw", "hidden_size": 104, "dropout": 0.2660308010009219, "num_layers": 4}, "time_since_restore": 484.7856192588806, "iterations_since_restore": 22}
{"iterations": 22, "train_loss": 0.006009343744100759, "test_loss": 0.1552207760636092, "Accuracy": 0.9664522058823529, "time_this_iter_s": 20.437238454818726, "done": false, "timesteps_total": 0, "episodes_total": 0, "training_iteration": 23, "trial_id": "6abc626f", "date": "2023-06-06_11-36-20", "timestamp": 1686051380, "time_total_s": 679.6330099105835, "pid": 3588, "hostname": "8fa062c8815e", "node_ip": "172.17.0.3", "config": {"input_size": 13, "output_size": 20, "tune_dir": "/workspaces/MLopdracht/models/ray", "data_dir": "/workspaces/MLopdracht/data/raw", "hidden_size": 104, "dropout": 0.2660308010009219, "num_layers": 4}, "time_since_restore": 505.22285771369934, "iterations_since_restore": 23}
{"iterations": 23, "train_loss": 0.014983430260948349, "test_loss": 0.13424398884971572, "Accuracy": 0.9715073529411765, "time_this_iter_s": 21.195225715637207, "done": false, "timesteps_total": 0, "episodes_total": 0, "training_iteration": 24, "trial_id": "6abc626f", "date": "2023-06-06_11-36-41", "timestamp": 1686051401, "time_total_s": 700.8282356262207, "pid": 3588, "hostname": "8fa062c8815e", "node_ip": "172.17.0.3", "config": {"input_size": 13, "output_size": 20, "tune_dir": "/workspaces/MLopdracht/models/ray", "data_dir": "/workspaces/MLopdracht/data/raw", "hidden_size": 104, "dropout": 0.2660308010009219, "num_layers": 4}, "time_since_restore": 526.4180834293365, "iterations_since_restore": 24}
{"iterations": 24, "train_loss": 0.03181947512553272, "test_loss": 0.1744603323561879, "Accuracy": 0.9600183823529411, "time_this_iter_s": 20.713801383972168, "done": false, "timesteps_total": 0, "episodes_total": 0, "training_iteration": 25, "trial_id": "6abc626f", "date": "2023-06-06_11-37-01", "timestamp": 1686051421, "time_total_s": 721.5420370101929, "pid": 3588, "hostname": "8fa062c8815e", "node_ip": "172.17.0.3", "config": {"input_size": 13, "output_size": 20, "tune_dir": "/workspaces/MLopdracht/models/ray", "data_dir": "/workspaces/MLopdracht/data/raw", "hidden_size": 104, "dropout": 0.2660308010009219, "num_layers": 4}, "time_since_restore": 547.1318848133087, "iterations_since_restore": 25}
{"iterations": 25, "train_loss": 0.0075795450434314755, "test_loss": 0.1847251794542364, "Accuracy": 0.9549632352941176, "time_this_iter_s": 20.512797832489014, "done": false, "timesteps_total": 0, "episodes_total": 0, "training_iteration": 26, "trial_id": "6abc626f", "date": "2023-06-06_11-37-22", "timestamp": 1686051442, "time_total_s": 742.0548348426819, "pid": 3588, "hostname": "8fa062c8815e", "node_ip": "172.17.0.3", "config": {"input_size": 13, "output_size": 20, "tune_dir": "/workspaces/MLopdracht/models/ray", "data_dir": "/workspaces/MLopdracht/data/raw", "hidden_size": 104, "dropout": 0.2660308010009219, "num_layers": 4}, "time_since_restore": 567.6446826457977, "iterations_since_restore": 26}
{"iterations": 26, "train_loss": 0.006482514345654495, "test_loss": 0.21359312826483373, "Accuracy": 0.9577205882352942, "time_this_iter_s": 21.38217854499817, "done": false, "timesteps_total": 0, "episodes_total": 0, "training_iteration": 27, "trial_id": "6abc626f", "date": "2023-06-06_11-37-43", "timestamp": 1686051463, "time_total_s": 763.43701338768, "pid": 3588, "hostname": "8fa062c8815e", "node_ip": "172.17.0.3", "config": {"input_size": 13, "output_size": 20, "tune_dir": "/workspaces/MLopdracht/models/ray", "data_dir": "/workspaces/MLopdracht/data/raw", "hidden_size": 104, "dropout": 0.2660308010009219, "num_layers": 4}, "time_since_restore": 589.0268611907959, "iterations_since_restore": 27}
{"iterations": 27, "train_loss": 0.008189098171870567, "test_loss": 0.27188821070098235, "Accuracy": 0.9494485294117647, "time_this_iter_s": 20.87214684486389, "done": false, "timesteps_total": 0, "episodes_total": 0, "training_iteration": 28, "trial_id": "6abc626f", "date": "2023-06-06_11-38-04", "timestamp": 1686051484, "time_total_s": 784.309160232544, "pid": 3588, "hostname": "8fa062c8815e", "node_ip": "172.17.0.3", "config": {"input_size": 13, "output_size": 20, "tune_dir": "/workspaces/MLopdracht/models/ray", "data_dir": "/workspaces/MLopdracht/data/raw", "hidden_size": 104, "dropout": 0.2660308010009219, "num_layers": 4}, "time_since_restore": 609.8990080356598, "iterations_since_restore": 28}
{"iterations": 28, "train_loss": 0.01611613758610227, "test_loss": 0.16262879553987125, "Accuracy": 0.9609375, "time_this_iter_s": 20.781885147094727, "done": false, "timesteps_total": 0, "episodes_total": 0, "training_iteration": 29, "trial_id": "6abc626f", "date": "2023-06-06_11-38-25", "timestamp": 1686051505, "time_total_s": 805.0910453796387, "pid": 3588, "hostname": "8fa062c8815e", "node_ip": "172.17.0.3", "config": {"input_size": 13, "output_size": 20, "tune_dir": "/workspaces/MLopdracht/models/ray", "data_dir": "/workspaces/MLopdracht/data/raw", "hidden_size": 104, "dropout": 0.2660308010009219, "num_layers": 4}, "time_since_restore": 630.6808931827545, "iterations_since_restore": 29}
{"iterations": 29, "train_loss": 0.019597443672732306, "test_loss": 0.19361246938933618, "Accuracy": 0.9586397058823529, "time_this_iter_s": 20.8410222530365, "done": false, "timesteps_total": 0, "episodes_total": 0, "training_iteration": 30, "trial_id": "6abc626f", "date": "2023-06-06_11-38-46", "timestamp": 1686051526, "time_total_s": 825.9320676326752, "pid": 3588, "hostname": "8fa062c8815e", "node_ip": "172.17.0.3", "config": {"input_size": 13, "output_size": 20, "tune_dir": "/workspaces/MLopdracht/models/ray", "data_dir": "/workspaces/MLopdracht/data/raw", "hidden_size": 104, "dropout": 0.2660308010009219, "num_layers": 4}, "time_since_restore": 651.521915435791, "iterations_since_restore": 30}
{"iterations": 30, "train_loss": 0.007174965111313849, "test_loss": 0.24111250291881495, "Accuracy": 0.9618566176470589, "time_this_iter_s": 21.160507440567017, "done": false, "timesteps_total": 0, "episodes_total": 0, "training_iteration": 31, "trial_id": "6abc626f", "date": "2023-06-06_11-39-07", "timestamp": 1686051547, "time_total_s": 847.0925750732422, "pid": 3588, "hostname": "8fa062c8815e", "node_ip": "172.17.0.3", "config": {"input_size": 13, "output_size": 20, "tune_dir": "/workspaces/MLopdracht/models/ray", "data_dir": "/workspaces/MLopdracht/data/raw", "hidden_size": 104, "dropout": 0.2660308010009219, "num_layers": 4}, "time_since_restore": 672.682422876358, "iterations_since_restore": 31}
{"iterations": 31, "train_loss": 0.0012978057959682119, "test_loss": 0.16785964049974128, "Accuracy": 0.9669117647058824, "time_this_iter_s": 20.81740641593933, "done": false, "timesteps_total": 0, "episodes_total": 0, "training_iteration": 32, "trial_id": "6abc626f", "date": "2023-06-06_11-39-28", "timestamp": 1686051568, "time_total_s": 867.9099814891815, "pid": 3588, "hostname": "8fa062c8815e", "node_ip": "172.17.0.3", "config": {"input_size": 13, "output_size": 20, "tune_dir": "/workspaces/MLopdracht/models/ray", "data_dir": "/workspaces/MLopdracht/data/raw", "hidden_size": 104, "dropout": 0.2660308010009219, "num_layers": 4}, "time_since_restore": 693.4998292922974, "iterations_since_restore": 32}
{"iterations": 32, "train_loss": 0.02191760531825565, "test_loss": 0.09900722166211755, "Accuracy": 0.9733455882352942, "time_this_iter_s": 20.66389751434326, "done": false, "timesteps_total": 0, "episodes_total": 0, "training_iteration": 33, "trial_id": "6abc626f", "date": "2023-06-06_11-39-49", "timestamp": 1686051589, "time_total_s": 888.5738790035248, "pid": 3588, "hostname": "8fa062c8815e", "node_ip": "172.17.0.3", "config": {"input_size": 13, "output_size": 20, "tune_dir": "/workspaces/MLopdracht/models/ray", "data_dir": "/workspaces/MLopdracht/data/raw", "hidden_size": 104, "dropout": 0.2660308010009219, "num_layers": 4}, "time_since_restore": 714.1637268066406, "iterations_since_restore": 33}
{"iterations": 33, "train_loss": 0.003559359323173463, "test_loss": 0.2594408713082564, "Accuracy": 0.9540441176470589, "time_this_iter_s": 20.847541570663452, "done": false, "timesteps_total": 0, "episodes_total": 0, "training_iteration": 34, "trial_id": "6abc626f", "date": "2023-06-06_11-40-09", "timestamp": 1686051609, "time_total_s": 909.4214205741882, "pid": 3588, "hostname": "8fa062c8815e", "node_ip": "172.17.0.3", "config": {"input_size": 13, "output_size": 20, "tune_dir": "/workspaces/MLopdracht/models/ray", "data_dir": "/workspaces/MLopdracht/data/raw", "hidden_size": 104, "dropout": 0.2660308010009219, "num_layers": 4}, "time_since_restore": 735.0112683773041, "iterations_since_restore": 34}
{"iterations": 34, "train_loss": 0.001575404303631569, "test_loss": 0.21005944835397874, "Accuracy": 0.9678308823529411, "time_this_iter_s": 21.05591917037964, "done": false, "timesteps_total": 0, "episodes_total": 0, "training_iteration": 35, "trial_id": "6abc626f", "date": "2023-06-06_11-40-30", "timestamp": 1686051630, "time_total_s": 930.4773397445679, "pid": 3588, "hostname": "8fa062c8815e", "node_ip": "172.17.0.3", "config": {"input_size": 13, "output_size": 20, "tune_dir": "/workspaces/MLopdracht/models/ray", "data_dir": "/workspaces/MLopdracht/data/raw", "hidden_size": 104, "dropout": 0.2660308010009219, "num_layers": 4}, "time_since_restore": 756.0671875476837, "iterations_since_restore": 35}
{"iterations": 35, "train_loss": 0.0004325895439533887, "test_loss": 0.21340836740872712, "Accuracy": 0.9650735294117647, "time_this_iter_s": 20.24203658103943, "done": false, "timesteps_total": 0, "episodes_total": 0, "training_iteration": 36, "trial_id": "6abc626f", "date": "2023-06-06_11-40-51", "timestamp": 1686051651, "time_total_s": 950.7193763256073, "pid": 3588, "hostname": "8fa062c8815e", "node_ip": "172.17.0.3", "config": {"input_size": 13, "output_size": 20, "tune_dir": "/workspaces/MLopdracht/models/ray", "data_dir": "/workspaces/MLopdracht/data/raw", "hidden_size": 104, "dropout": 0.2660308010009219, "num_layers": 4}, "time_since_restore": 776.3092241287231, "iterations_since_restore": 36}
{"iterations": 36, "train_loss": 0.0003682066988368356, "test_loss": 0.20035608450223877, "Accuracy": 0.9664522058823529, "time_this_iter_s": 21.338799953460693, "done": false, "timesteps_total": 0, "episodes_total": 0, "training_iteration": 37, "trial_id": "6abc626f", "date": "2023-06-06_11-41-12", "timestamp": 1686051672, "time_total_s": 972.058176279068, "pid": 3588, "hostname": "8fa062c8815e", "node_ip": "172.17.0.3", "config": {"input_size": 13, "output_size": 20, "tune_dir": "/workspaces/MLopdracht/models/ray", "data_dir": "/workspaces/MLopdracht/data/raw", "hidden_size": 104, "dropout": 0.2660308010009219, "num_layers": 4}, "time_since_restore": 797.6480240821838, "iterations_since_restore": 37}
{"iterations": 37, "train_loss": 0.0002558746888910904, "test_loss": 0.20139763070865763, "Accuracy": 0.9659926470588235, "time_this_iter_s": 20.451802253723145, "done": false, "timesteps_total": 0, "episodes_total": 0, "training_iteration": 38, "trial_id": "6abc626f", "date": "2023-06-06_11-41-32", "timestamp": 1686051692, "time_total_s": 992.5099785327911, "pid": 3588, "hostname": "8fa062c8815e", "node_ip": "172.17.0.3", "config": {"input_size": 13, "output_size": 20, "tune_dir": "/workspaces/MLopdracht/models/ray", "data_dir": "/workspaces/MLopdracht/data/raw", "hidden_size": 104, "dropout": 0.2660308010009219, "num_layers": 4}, "time_since_restore": 818.099826335907, "iterations_since_restore": 38}
{"iterations": 38, "train_loss": 0.00024774757852338175, "test_loss": 0.20321931267458507, "Accuracy": 0.9655330882352942, "time_this_iter_s": 20.404614210128784, "done": false, "timesteps_total": 0, "episodes_total": 0, "training_iteration": 39, "trial_id": "6abc626f", "date": "2023-06-06_11-41-53", "timestamp": 1686051713, "time_total_s": 1012.9145927429199, "pid": 3588, "hostname": "8fa062c8815e", "node_ip": "172.17.0.3", "config": {"input_size": 13, "output_size": 20, "tune_dir": "/workspaces/MLopdracht/models/ray", "data_dir": "/workspaces/MLopdracht/data/raw", "hidden_size": 104, "dropout": 0.2660308010009219, "num_layers": 4}, "time_since_restore": 838.5044405460358, "iterations_since_restore": 39}
{"iterations": 39, "train_loss": 0.00018449681893683905, "test_loss": 0.20219897252194213, "Accuracy": 0.9650735294117647, "time_this_iter_s": 20.41864514350891, "done": false, "timesteps_total": 0, "episodes_total": 0, "training_iteration": 40, "trial_id": "6abc626f", "date": "2023-06-06_11-42-13", "timestamp": 1686051733, "time_total_s": 1033.3332378864288, "pid": 3588, "hostname": "8fa062c8815e", "node_ip": "172.17.0.3", "config": {"input_size": 13, "output_size": 20, "tune_dir": "/workspaces/MLopdracht/models/ray", "data_dir": "/workspaces/MLopdracht/data/raw", "hidden_size": 104, "dropout": 0.2660308010009219, "num_layers": 4}, "time_since_restore": 858.9230856895447, "iterations_since_restore": 40}
{"iterations": 40, "train_loss": 0.0004231520296635052, "test_loss": 0.18945680505695398, "Accuracy": 0.9678308823529411, "time_this_iter_s": 19.926129817962646, "done": false, "timesteps_total": 0, "episodes_total": 0, "training_iteration": 41, "trial_id": "6abc626f", "date": "2023-06-06_11-42-33", "timestamp": 1686051753, "time_total_s": 1053.2593677043915, "pid": 3588, "hostname": "8fa062c8815e", "node_ip": "172.17.0.3", "config": {"input_size": 13, "output_size": 20, "tune_dir": "/workspaces/MLopdracht/models/ray", "data_dir": "/workspaces/MLopdracht/data/raw", "hidden_size": 104, "dropout": 0.2660308010009219, "num_layers": 4}, "time_since_restore": 878.8492155075073, "iterations_since_restore": 41}
{"iterations": 41, "train_loss": 0.00016917665568841575, "test_loss": 0.20420831583514348, "Accuracy": 0.9678308823529411, "time_this_iter_s": 19.071104764938354, "done": false, "timesteps_total": 0, "episodes_total": 0, "training_iteration": 42, "trial_id": "6abc626f", "date": "2023-06-06_11-42-52", "timestamp": 1686051772, "time_total_s": 1072.3304724693298, "pid": 3588, "hostname": "8fa062c8815e", "node_ip": "172.17.0.3", "config": {"input_size": 13, "output_size": 20, "tune_dir": "/workspaces/MLopdracht/models/ray", "data_dir": "/workspaces/MLopdracht/data/raw", "hidden_size": 104, "dropout": 0.2660308010009219, "num_layers": 4}, "time_since_restore": 897.9203202724457, "iterations_since_restore": 42}
{"iterations": 42, "train_loss": 0.0001350611616623954, "test_loss": 0.20038937863720255, "Accuracy": 0.9669117647058824, "time_this_iter_s": 18.87804341316223, "done": false, "timesteps_total": 0, "episodes_total": 0, "training_iteration": 43, "trial_id": "6abc626f", "date": "2023-06-06_11-43-11", "timestamp": 1686051791, "time_total_s": 1091.208515882492, "pid": 3588, "hostname": "8fa062c8815e", "node_ip": "172.17.0.3", "config": {"input_size": 13, "output_size": 20, "tune_dir": "/workspaces/MLopdracht/models/ray", "data_dir": "/workspaces/MLopdracht/data/raw", "hidden_size": 104, "dropout": 0.2660308010009219, "num_layers": 4}, "time_since_restore": 916.7983636856079, "iterations_since_restore": 43}
{"iterations": 43, "train_loss": 0.00012653538638932713, "test_loss": 0.20563199378621527, "Accuracy": 0.9664522058823529, "time_this_iter_s": 19.114588260650635, "done": false, "timesteps_total": 0, "episodes_total": 0, "training_iteration": 44, "trial_id": "6abc626f", "date": "2023-06-06_11-43-30", "timestamp": 1686051810, "time_total_s": 1110.3231041431427, "pid": 3588, "hostname": "8fa062c8815e", "node_ip": "172.17.0.3", "config": {"input_size": 13, "output_size": 20, "tune_dir": "/workspaces/MLopdracht/models/ray", "data_dir": "/workspaces/MLopdracht/data/raw", "hidden_size": 104, "dropout": 0.2660308010009219, "num_layers": 4}, "time_since_restore": 935.9129519462585, "iterations_since_restore": 44}
{"iterations": 44, "train_loss": 0.00011694637191574003, "test_loss": 0.2177837801673912, "Accuracy": 0.9641544117647058, "time_this_iter_s": 18.82734203338623, "done": false, "timesteps_total": 0, "episodes_total": 0, "training_iteration": 45, "trial_id": "6abc626f", "date": "2023-06-06_11-43-49", "timestamp": 1686051829, "time_total_s": 1129.150446176529, "pid": 3588, "hostname": "8fa062c8815e", "node_ip": "172.17.0.3", "config": {"input_size": 13, "output_size": 20, "tune_dir": "/workspaces/MLopdracht/models/ray", "data_dir": "/workspaces/MLopdracht/data/raw", "hidden_size": 104, "dropout": 0.2660308010009219, "num_layers": 4}, "time_since_restore": 954.7402939796448, "iterations_since_restore": 45}
{"iterations": 45, "train_loss": 9.824138057578662e-05, "test_loss": 0.2042924861809083, "Accuracy": 0.9664522058823529, "time_this_iter_s": 19.119089365005493, "done": false, "timesteps_total": 0, "episodes_total": 0, "training_iteration": 46, "trial_id": "6abc626f", "date": "2023-06-06_11-44-08", "timestamp": 1686051848, "time_total_s": 1148.2695355415344, "pid": 3588, "hostname": "8fa062c8815e", "node_ip": "172.17.0.3", "config": {"input_size": 13, "output_size": 20, "tune_dir": "/workspaces/MLopdracht/models/ray", "data_dir": "/workspaces/MLopdracht/data/raw", "hidden_size": 104, "dropout": 0.2660308010009219, "num_layers": 4}, "time_since_restore": 973.8593833446503, "iterations_since_restore": 46}
{"iterations": 46, "train_loss": 9.59248819235301e-05, "test_loss": 0.21946327156108644, "Accuracy": 0.9632352941176471, "time_this_iter_s": 18.930670738220215, "done": false, "timesteps_total": 0, "episodes_total": 0, "training_iteration": 47, "trial_id": "6abc626f", "date": "2023-06-06_11-44-27", "timestamp": 1686051867, "time_total_s": 1167.2002062797546, "pid": 3588, "hostname": "8fa062c8815e", "node_ip": "172.17.0.3", "config": {"input_size": 13, "output_size": 20, "tune_dir": "/workspaces/MLopdracht/models/ray", "data_dir": "/workspaces/MLopdracht/data/raw", "hidden_size": 104, "dropout": 0.2660308010009219, "num_layers": 4}, "time_since_restore": 992.7900540828705, "iterations_since_restore": 47}
{"iterations": 47, "train_loss": 9.212213179796766e-05, "test_loss": 0.21157988358305269, "Accuracy": 0.9650735294117647, "time_this_iter_s": 19.055529832839966, "done": false, "timesteps_total": 0, "episodes_total": 0, "training_iteration": 48, "trial_id": "6abc626f", "date": "2023-06-06_11-44-46", "timestamp": 1686051886, "time_total_s": 1186.2557361125946, "pid": 3588, "hostname": "8fa062c8815e", "node_ip": "172.17.0.3", "config": {"input_size": 13, "output_size": 20, "tune_dir": "/workspaces/MLopdracht/models/ray", "data_dir": "/workspaces/MLopdracht/data/raw", "hidden_size": 104, "dropout": 0.2660308010009219, "num_layers": 4}, "time_since_restore": 1011.8455839157104, "iterations_since_restore": 48}
{"iterations": 48, "train_loss": 0.09348173974368604, "test_loss": 0.20092195265597718, "Accuracy": 0.9508272058823529, "time_this_iter_s": 19.01927661895752, "done": false, "timesteps_total": 0, "episodes_total": 0, "training_iteration": 49, "trial_id": "6abc626f", "date": "2023-06-06_11-45-05", "timestamp": 1686051905, "time_total_s": 1205.2750127315521, "pid": 3588, "hostname": "8fa062c8815e", "node_ip": "172.17.0.3", "config": {"input_size": 13, "output_size": 20, "tune_dir": "/workspaces/MLopdracht/models/ray", "data_dir": "/workspaces/MLopdracht/data/raw", "hidden_size": 104, "dropout": 0.2660308010009219, "num_layers": 4}, "time_since_restore": 1030.864860534668, "iterations_since_restore": 49}
{"iterations": 49, "train_loss": 0.02036030516785669, "test_loss": 0.13474418451369274, "Accuracy": 0.9710477941176471, "time_this_iter_s": 18.994382619857788, "done": false, "timesteps_total": 0, "episodes_total": 0, "training_iteration": 50, "trial_id": "6abc626f", "date": "2023-06-06_11-45-24", "timestamp": 1686051924, "time_total_s": 1224.26939535141, "pid": 3588, "hostname": "8fa062c8815e", "node_ip": "172.17.0.3", "config": {"input_size": 13, "output_size": 20, "tune_dir": "/workspaces/MLopdracht/models/ray", "data_dir": "/workspaces/MLopdracht/data/raw", "hidden_size": 104, "dropout": 0.2660308010009219, "num_layers": 4}, "time_since_restore": 1049.8592431545258, "iterations_since_restore": 50}
